_lib_engine.abi3.so
nfstream/__init__.py
nfstream/anonymizer.py
nfstream/flow.py
nfstream/meter.py
nfstream/plugin.py
nfstream/streamer.py
nfstream/system.py
nfstream/utils.py
nfstream/engine/__init__.py
nfstream/engine/engine.py
nfstream/engine/engine_build.py
nfstream/engine/dependencies/libpcap/testprogs/visopts.py
nfstream/engine/dependencies/nDPI/doc/conf.py
nfstream/engine/dependencies/nDPI/example/ndpi2timeline.py
nfstream/engine/dependencies/nDPI/python/ndpi_example.py
nfstream/engine/dependencies/nDPI/python/setup.py
nfstream/engine/dependencies/nDPI/python/tests.py
nfstream/engine/dependencies/nDPI/python/ndpi/__init__.py
nfstream/engine/dependencies/nDPI/python/ndpi/ndpi.py
nfstream/engine/dependencies/nDPI/python/ndpi/ndpi_build.py
nfstream/engine/dependencies/nDPI/utils/google.py
nfstream/engine/dependencies/nDPI/utils/ipaddr2list.py
nfstream/engine/dependencies/nDPI/utils/mergeipaddrlist.py
nfstream/plugins/__init__.py
nfstream/plugins/dhcp.py
nfstream/plugins/ja4.py
nfstream/plugins/mdns.py
nfstream/plugins/slicer.py
nfstream/plugins/splt.py
nfstream/plugins/wfeatures.py
nfstream-6.5.4.dist-info/METADATA
nfstream-6.5.4.dist-info/WHEEL
nfstream-6.5.4.dist-info/top_level.txt
nfstream-6.5.4.dist-info/RECORD
nfstream-6.5.4.dist-info/licenses/LICENSE
