Metadata-Version: 2.4
Name: nfstream
Version: 6.5.4
Summary: A Flexible Network Data Analysis Framework
Home-page: https://www.nfstream.org/
Author: Zied Aouini
Author-email: aouinizied@gmail.com
License: LGPLv3
Project-URL: GitHub, https://github.com/nfstream/nfstream
Platform: Linux
Platform: Mac OS-X
Platform: Windows
Platform: Unix
Classifier: Development Status :: 5 - Production/Stable
Classifier: License :: OSI Approved :: GNU Lesser General Public License v3 or later (LGPLv3+)
Classifier: Intended Audience :: Telecommunications Industry
Classifier: Intended Audience :: Information Technology
Classifier: Intended Audience :: System Administrators
Classifier: Intended Audience :: Science/Research
Classifier: Intended Audience :: Developers
Classifier: Programming Language :: Python :: 3 :: Only
Classifier: Programming Language :: Python :: 3.9
Classifier: Programming Language :: Python :: 3.10
Classifier: Programming Language :: Python :: 3.11
Classifier: Programming Language :: Python :: 3.12
Classifier: Programming Language :: Python :: 3.13
Classifier: Programming Language :: Python :: 3.14
Classifier: Topic :: Security
Classifier: Topic :: Internet :: Log Analysis
Classifier: Topic :: System :: Networking :: Monitoring
Classifier: Topic :: Scientific/Engineering :: Artificial Intelligence
License-File: LICENSE
Requires-Dist: cffi>=1.15.0
Requires-Dist: psutil>=5.8.0
Requires-Dist: dpkt>=1.9.7
Requires-Dist: numpy>=1.19.5
Requires-Dist: pandas>=1.1.5
Dynamic: author
Dynamic: author-email
Dynamic: classifier
Dynamic: description
Dynamic: description-content-type
Dynamic: home-page
Dynamic: license
Dynamic: license-file
Dynamic: platform
Dynamic: project-url
Dynamic: requires-dist
Dynamic: summary
